[
  {
    "id": "mpgzhvqz-lvhuc",
    "name": "Burcsa Matei",
    "email": "burcsamatei@outlook.com",
    "phone": "+40756795162",
    "message": "Acesta este un mesaj de test si trebuie trata ca atare.",
    "ip": "188.27.146.118",
    "created_at": "2026-05-22T13:57:28.187Z",
    "read": true
  },
  {
    "id": "mph43iyp-od3k2",
    "name": "Burcsa Matei",
    "email": "burcsamatei@outlook.com",
    "phone": "+40756795162",
    "message": "Acesta este un mesaj de test si trebuie tratat ca atare.",
    "ip": "188.27.146.118",
    "created_at": "2026-05-22T16:06:16.513Z"
  },
  {
    "id": "mph44htz-s2pm0",
    "name": "Test",
    "email": "test@test.com",
    "phone": "0751000000",
    "message": "test mesaj diagnostic",
    "ip": "188.27.146.118",
    "created_at": "2026-05-22T16:07:01.703Z",
    "read": true
  },
  {
    "id": "mph44xvf-id5ne",
    "name": "Test Diagnostic",
    "email": "test@test.com",
    "phone": "0751000000",
    "message": "Mesaj de test diagnostic - verificare API",
    "ip": "188.27.146.118",
    "created_at": "2026-05-22T16:07:22.491Z"
  },
  {
    "id": "mph4554o-schjl",
    "name": "Test Diagnostic 2",
    "email": "test@test.com",
    "phone": null,
    "message": "Mesaj test minim 10 caractere",
    "ip": "188.27.146.118",
    "created_at": "2026-05-22T16:07:31.896Z"
  },
  {
    "id": "mph45ewt-uelji",
    "name": "Debug Test",
    "email": "debug@test.com",
    "phone": null,
    "message": "Debug message longer than 10 chars",
    "ip": "188.27.146.118",
    "created_at": "2026-05-22T16:07:44.573Z"
  }
]